aws_s3_ops/__init__.py
aws_s3_ops/aws_s3_ops.py
aws_s3_ops/exceptions.py
aws_s3_ops-1.0.0.dist-info/LICENSE.txt
aws_s3_ops-1.0.0.dist-info/METADATA
aws_s3_ops-1.0.0.dist-info/WHEEL
aws_s3_ops-1.0.0.dist-info/top_level.txt
aws_s3_ops-1.0.0.dist-info/RECORD
