Metadata-Version: 2.1
Name: aws-s3-ops
Version: 1.0.0
Summary: This repository contains code for input and output operations on s3 buckets
Home-page: https://github.com/AashimaYuthika/aws_s3_ops
Author: Aashima Yuthika
Author-email: aashima.yuthika@gmail.com
License: UNKNOWN
Platform: UNKNOWN
Classifier: Development Status :: 3 - Alpha
Classifier: Intended Audience :: Developers
Classifier: Topic :: Software Development :: Build Tools
Classifier: License :: OSI Approved :: MIT License
Classifier: Programming Language :: Python :: 2
Classifier: Programming Language :: Python :: 3.6
Requires-Python: >=2.7, <4
Requires-Dist: boto3
Requires-Dist: pandas
Provides-Extra: dev
Requires-Dist: check-manifest ; extra == 'dev'
Provides-Extra: test
Requires-Dist: coverage ; extra == 'test'
